uritemplate/__init__.py
uritemplate/api.py
uritemplate/orderedset.py
uritemplate/py.typed
uritemplate/template.py
uritemplate/variable.py
uritemplate-4.1.0.dist-info/LICENSE
uritemplate-4.1.0.dist-info/METADATA
uritemplate-4.1.0.dist-info/WHEEL
uritemplate-4.1.0.dist-info/top_level.txt
uritemplate-4.1.0.dist-info/RECORD
